Workbook

Sheet Raw Sales
A1: Date | B1: Order ID | C1: Salesperson | D1: Product | E1: Category | F1: Units | G1: Unit Price | H1: Sales Amount | I1: Payment Method | J1: Status
A2: 46296 | B2: ORD-1001 | C2: Asha | D2: Notebook | E2: Stationery | F2: 10 | G2: 45 | H2: =F2*G2 | I2: UPI | J2: Completed
A3: 46296 | B3: ORD-1002 | C3: Rahul | D3: Pen Set | E3: Stationery | F3: 8 | G3: 80 | H3: =F3*G3 | I3: Card | J3: Completed
A4: 46297 | B4: ORD-1003 | C4: Meera | D4: Water Bottle | E4: Accessories | F4: 5 | G4: 250 | H4: =F4*G4 | I4: Cash | J4: Completed
A5: 46298 | B5: ORD-1004 | C5: Asha | D5: Backpack | E5: Bags | F5: 2 | G5: 1200 | H5: =F5*G5 | I5: UPI | J5: Completed
A6: 46299 | B6: ORD-1005 | C6: Imran | D6: Notebook | E6: Stationery | F6: 12 | G6: 45 | H6: =F6*G6 | I6: Cash | J6: Completed
A7: 46300 | B7: ORD-1006 | C7: Meera | D7: Desk Lamp | E7: Home | F7: 3 | G7: 650 | H7: =F7*G7 | I7: Card | J7: Completed
A8: 46301 | B8: ORD-1007 | C8: Rahul | D8: Pen Set | E8: Stationery | F8: 6 | G8: 80 | H8: =F8*G8 | I8: UPI | J8: Returned
A9: 46302 | B9: ORD-1008 | C9: Asha | D9: Water Bottle | E9: Accessories | F9: 4 | G9: 250 | H9: =F9*G9 | I9: Card | J9: Completed
A10: 46303 | B10: ORD-1009 | C10: Imran | D10: Backpack | E10: Bags | F10: 1 | G10: 1200 | H10: =F10*G10 | I10: UPI | J10: Completed
A11: 46304 | B11: ORD-1010 | C11: Meera | D11: Notebook | E11: Stationery | F11: 20 | G11: 45 | H11: =F11*G11 | I11: Cash | J11: Completed
A12: 46305 | B12: ORD-1011 | C12: Rahul | D12: Desk Lamp | E12: Home | F12: 2 | G12: 650 | H12: =F12*G12 | I12: Card | J12: Completed
A13: 46306 | B13: ORD-1012 | C13: Asha | D13: Pen Set | E13: Stationery | F13: 5 | G13: 80 | H13: =F13*G13 | I13: UPI | J13: Completed
... A21: 46314 | B21: ORD-1020 | C21: Asha | D21: Notebook | E21: Stationery | F21: 25 | G21: 45 | H21: =F21*G21 | I21: Card | J21: Completed
H22: =IF(OR(F22="",G22=""),"",F22*G22)
H23: =IF(OR(F23="",G23=""),"",F23*G23)
H24: =IF(OR(F24="",G24=""),"",F24*G24)
H25: =IF(OR(F25="",G25=""),"",F25*G25)
H26: =IF(OR(F26="",G26=""),"",F26*G26)
H27: =IF(OR(F27="",G27=""),"",F27*G27)
H28: =IF(OR(F28="",G28=""),"",F28*G28)
H29: =IF(OR(F29="",G29=""),"",F29*G29)
H30: =IF(OR(F30="",G30=""),"",F30*G30)
H31: =IF(OR(F31="",G31=""),"",F31*G31)
H32: =IF(OR(F32="",G32=""),"",F32*G32)
H33: =IF(OR(F33="",G33=""),"",F33*G33)
... H51: =IF(OR(F51="",G51=""),"",F51*G51)

Sheet Summary
A1: SALES TRACKER — SUMMARY
A2: Sample reporting period: October 2026 | Update dates below as needed
A4: Daily totals
A5: Date | B5: Total Sales | C5: Completed Sales | D5: Order Count
A6: 46296 | B6: =SUMIFS('Raw Sales'!$H$2:$H$51,'Raw Sales'!$A$2:$A$51,A6) | C6: =SUMIFS('Raw Sales'!$H$2:$H$51,'Raw Sales'!$A$2:$A$51,A6,'Raw Sales'!$J$2:$J$51,"Completed") | D6: =COUNTIFS('Raw Sales'!$A$2:$A$51,A6,'Raw Sales'!$B$2:$B$51,"<>")
A7: 46297 | B7: =SUMIFS('Raw Sales'!$H$2:$H$51,'Raw Sales'!$A$2:$A$51,A7) | C7: =SUMIFS('Raw Sales'!$H$2:$H$51,'Raw Sales'!$A$2:$A$51,A7,'Raw Sales'!$J$2:$J$51,"Completed") | D7: =COUNTIFS('Raw Sales'!$A$2:$A$51,A7,'Raw Sales'!$B$2:$B$51,"<>")
A8: 46298 | B8: =SUMIFS('Raw Sales'!$H$2:$H$51,'Raw Sales'!$A$2:$A$51,A8) | C8: =SUMIFS('Raw Sales'!$H$2:$H$51,'Raw Sales'!$A$2:$A$51,A8,'Raw Sales'!$J$2:$J$51,"Completed") | D8: =COUNTIFS('Raw Sales'!$A$2:$A$51,A8,'Raw Sales'!$B$2:$B$51,"<>")
A9: 46299 | B9: =SUMIFS('Raw Sales'!$H$2:$H$51,'Raw Sales'!$A$2:$A$51,A9) | C9: =SUMIFS('Raw Sales'!$H$2:$H$51,'Raw Sales'!$A$2:$A$51,A9,'Raw Sales'!$J$2:$J$51,"Completed") | D9: =COUNTIFS('Raw Sales'!$A$2:$A$51,A9,'Raw Sales'!$B$2:$B$51,"<>")
A10: 46300 | B10: =SUMIFS('Raw Sales'!$H$2:$H$51,'Raw Sales'!$A$2:$A$51,A10) | C10: =SUMIFS('Raw Sales'!$H$2:$H$51,'Raw Sales'!$A$2:$A$51,A10,'Raw Sales'!$J$2:$J$51,"Completed") | D10: =COUNTIFS('Raw Sales'!$A$2:$A$51,A10,'Raw Sales'!$B$2:$B$51,"<>")
A11: 46301 | B11: =SUMIFS('Raw Sales'!$H$2:$H$51,'Raw Sales'!$A$2:$A$51,A11) | C11: =SUMIFS('Raw Sales'!$H$2:$H$51,'Raw Sales'!$A$2:$A$51,A11,'Raw Sales'!$J$2:$J$51,"Completed") | D11: =COUNTIFS('Raw Sales'!$A$2:$A$51,A11,'Raw Sales'!$B$2:$B$51,"<>")
A12: 46302 | B12: =SUMIFS('Raw Sales'!$H$2:$H$51,'Raw Sales'!$A$2:$A$51,A12) | C12: =SUMIFS('Raw Sales'!$H$2:$H$51,'Raw Sales'!$A$2:$A$51,A12,'Raw Sales'!$J$2:$J$51,"Completed") | D12: =COUNTIFS('Raw Sales'!$A$2:$A$51,A12,'Raw Sales'!$B$2:$B$51,"<>")
A13: 46303 | B13: =SUMIFS('Raw Sales'!$H$2:$H$51,'Raw Sales'!$A$2:$A$51,A13) | C13: =SUMIFS('Raw Sales'!$H$2:$H$51,'Raw Sales'!$A$2:$A$51,A13,'Raw Sales'!$J$2:$J$51,"Completed") | D13: =COUNTIFS('Raw Sales'!$A$2:$A$51,A13,'Raw Sales'!$B$2:$B$51,"<>")
A14: 46304 | B14: =SUMIFS('Raw Sales'!$H$2:$H$51,'Raw Sales'!$A$2:$A$51,A14) | C14: =SUMIFS('Raw Sales'!$H$2:$H$51,'Raw Sales'!$A$2:$A$51,A14,'Raw Sales'!$J$2:$J$51,"Completed") | D14: =COUNTIFS('Raw Sales'!$A$2:$A$51,A14,'Raw Sales'!$B$2:$B$51,"<>")
A15: 46305 | B15: =SUMIFS('Raw Sales'!$H$2:$H$51,'Raw Sales'!$A$2:$A$51,A15) | C15: =SUMIFS('Raw Sales'!$H$2:$H$51,'Raw Sales'!$A$2:$A$51,A15,'Raw Sales'!$J$2:$J$51,"Completed") | D15: =COUNTIFS('Raw Sales'!$A$2:$A$51,A15,'Raw Sales'!$B$2:$B$51,"<>")
A16: 46306 | B16: =SUMIFS('Raw Sales'!$H$2:$H$51,'Raw Sales'!$A$2:$A$51,A16) | C16: =SUMIFS('Raw Sales'!$H$2:$H$51,'Raw Sales'!$A$2:$A$51,A16,'Raw Sales'!$J$2:$J$51,"Completed") | D16: =COUNTIFS('Raw Sales'!$A$2:$A$51,A16,'Raw Sales'!$B$2:$B$51,"<>")
A17: 46307 | B17: =SUMIFS('Raw Sales'!$H$2:$H$51,'Raw Sales'!$A$2:$A$51,A17) | C17: =SUMIFS('Raw Sales'!$H$2:$H$51,'Raw Sales'!$A$2:$A$51,A17,'Raw Sales'!$J$2:$J$51,"Completed") | D17: =COUNTIFS('Raw Sales'!$A$2:$A$51,A17,'Raw Sales'!$B$2:$B$51,"<>")
... A36: 46326 | B36: =SUMIFS('Raw Sales'!$H$2:$H$51,'Raw Sales'!$A$2:$A$51,A36) | C36: =SUMIFS('Raw Sales'!$H$2:$H$51,'Raw Sales'!$A$2:$A$51,A36,'Raw Sales'!$J$2:$J$51,"Completed") | D36: =COUNTIFS('Raw Sales'!$A$2:$A$51,A36,'Raw Sales'!$B$2:$B$51,"<>")
A39: Weekly totals (Monday–Sunday)
A40: Week Start | B40: Week End | C40: Total Sales | D40: Completed Sales
A41: 46293 | B41: 46299 | C41: =SUMIFS('Raw Sales'!$H$2:$H$51,'Raw Sales'!$A$2:$A$51,">="&A41,'Raw Sales'!$A$2:$A$51,"<="&B41) | D41: =SUMIFS('Raw Sales'!$H$2:$H$51,'Raw Sales'!$A$2:$A$51,">="&A41,'Raw Sales'!$A$2:$A$51,"<="&B41,'Raw Sales'!$J$2:$J$51,"Completed")
A42: 46300 | B42: 46306 | C42: =SUMIFS('Raw Sales'!$H$2:$H$51,'Raw Sales'!$A$2:$A$51,">="&A42,'Raw Sales'!$A$2:$A$51,"<="&B42) | D42: =SUMIFS('Raw Sales'!$H$2:$H$51,'Raw Sales'!$A$2:$A$51,">="&A42,'Raw Sales'!$A$2:$A$51,"<="&B42,'Raw Sales'!$J$2:$J$51,"Completed")
A43: 46307 | B43: 46313 | C43: =SUMIFS('Raw Sales'!$H$2:$H$51,'Raw Sales'!$A$2:$A$51,">="&A43,'Raw Sales'!$A$2:$A$51,"<="&B43) | D43: =SUMIFS('Raw Sales'!$H$2:$H$51,'Raw Sales'!$A$2:$A$51,">="&A43,'Raw Sales'!$A$2:$A$51,"<="&B43,'Raw Sales'!$J$2:$J$51,"Completed")
A44: 46314 | B44: 46320 | C44: =SUMIFS('Raw Sales'!$H$2:$H$51,'Raw Sales'!$A$2:$A$51,">="&A44,'Raw Sales'!$A$2:$A$51,"<="&B44) | D44: =SUMIFS('Raw Sales'!$H$2:$H$51,'Raw Sales'!$A$2:$A$51,">="&A44,'Raw Sales'!$A$2:$A$51,"<="&B44,'Raw Sales'!$J$2:$J$51,"Completed")
A45: 46321 | B45: 46327 | C45: =SUMIFS('Raw Sales'!$H$2:$H$51,'Raw Sales'!$A$2:$A$51,">="&A45,'Raw Sales'!$A$2:$A$51,"<="&B45) | D45: =SUMIFS('Raw Sales'!$H$2:$H$51,'Raw Sales'!$A$2:$A$51,">="&A45,'Raw Sales'!$A$2:$A$51,"<="&B45,'Raw Sales'!$J$2:$J$51,"Completed")
A49: Monthly totals
A50: Month Start | B50: Month End | C50: Total Sales | D50: Completed Sales | E50: Order Count
A51: 46296 | B51: 46326 | C51: =SUMIFS('Raw Sales'!$H$2:$H$51,'Raw Sales'!$A$2:$A$51,">="&A51,'Raw Sales'!$A$2:$A$51,"<="&B51) | D51: =SUMIFS('Raw Sales'!$H$2:$H$51,'Raw Sales'!$A$2:$A$51,">="&A51,'Raw Sales'!$A$2:$A$51,"<="&B51,'Raw Sales'!$J$2:$J$51,"Completed") | E51: =COUNTIFS('Raw Sales'!$A$2:$A$51,">="&A51,'Raw Sales'!$A$2:$A$51,"<="&B51,'Raw Sales'!$B$2:$B$51,"<>")
A52: 46327 | B52: 46356 | C52: =SUMIFS('Raw Sales'!$H$2:$H$51,'Raw Sales'!$A$2:$A$51,">="&A52,'Raw Sales'!$A$2:$A$51,"<="&B52) | D52: =SUMIFS('Raw Sales'!$H$2:$H$51,'Raw Sales'!$A$2:$A$51,">="&A52,'Raw Sales'!$A$2:$A$51,"<="&B52,'Raw Sales'!$J$2:$J$51,"Completed") | E52: =COUNTIFS('Raw Sales'!$A$2:$A$51,">="&A52,'Raw Sales'!$A$2:$A$51,"<="&B52,'Raw Sales'!$B$2:$B$51,"<>")
A53: 46357 | B53: 46387 | C53: =SUMIFS('Raw Sales'!$H$2:$H$51,'Raw Sales'!$A$2:$A$51,">="&A53,'Raw Sales'!$A$2:$A$51,"<="&B53) | D53: =SUMIFS('Raw Sales'!$H$2:$H$51,'Raw Sales'!$A$2:$A$51,">="&A53,'Raw Sales'!$A$2:$A$51,"<="&B53,'Raw Sales'!$J$2:$J$51,"Completed") | E53: =COUNTIFS('Raw Sales'!$A$2:$A$51,">="&A53,'Raw Sales'!$A$2:$A$51,"<="&B53,'Raw Sales'!$B$2:$B$51,"<>")

Sheet Read Me
A1: SALES TRACKER — QUICK START
A2: Purpose | B2: Enter sales only in the Raw Sales tab. The Summary tab calculates daily, weekly, and monthly totals.
A3: Step 1 | B3: Open Raw Sales and add one row per order. Do not overwrite the formula in Sales Amount (column H).
A4: Step 2 | B4: Use the dropdowns for salesperson, category, payment method, and status. Units must be a positive whole number; unit price must be zero or more.
A5: Step 3 | B5: Check the Summary tab for daily totals, Monday–Sunday weekly totals, and monthly totals.
A6: Step 4 | B6: To use in Google Sheets: upload the .xlsx file to Google Drive, then choose Open with → Google Sheets. Check formulas after conversion.
A7: Formula logic | B7: Sales Amount = Units × Unit Price. SUMIFS is used with date boundaries for daily, weekly, and monthly sales; COUNTIFS counts orders.
A8: Important | B8: Sample data is fictional and for demonstration only. Replace or append records for real use. The workbook has formula-ready rows through row 51.
A9: Manual check | B9: Sample data total sales = ₹25,010.00 across 20 orders. One returned order is included in gross sales; Completed Sales excludes the returned order.
